{
  "league_id": 43384,
  "start_date": "2026-07-12",
  "days": 5,
  "date_range": "Jul 12\u201316",
  "cached": false,
  "pitchers": [
    {
      "name": "Jr Ritchie",
      "date": "2026-07-12",
      "pitcher_team": "ATL",
      "opponent_team": "STL",
      "home_away": "away",
      "game_time_pt": "11:15 AM PT",
      "availability": "free_agent",
      "stats": {
        "wins": 1,
        "losses": 2,
        "era": "4.60",
        "whip": "1.47",
        "innings_pitched": "45.0",
        "strikeouts": 42,
        "highlights": {
          "era": null,
          "whip": null,
          "k_per_9": null
        }
      },
      "opposing_pitcher_name": "Dustin May",
      "yahoo_gamelog_url": "https://sports.yahoo.com/mlb/players/60071/gamelog/",
      "opponent_highlight": null
    },
    {
      "name": "German Marquez",
      "date": "2026-07-12",
      "pitcher_team": "SD",
      "opponent_team": "TOR",
      "home_away": "home",
      "game_time_pt": "1:10 PM PT",
      "availability": "free_agent",
      "stats": {
        "wins": 4,
        "losses": 2,
        "era": "5.02",
        "whip": "1.43",
        "innings_pitched": "37.2",
        "strikeouts": 24,
        "highlights": {
          "era": "warn",
          "whip": null,
          "k_per_9": null
        }
      },
      "opposing_pitcher_name": "Kevin Gausman",
      "yahoo_gamelog_url": "https://sports.yahoo.com/mlb/players/10402/gamelog/",
      "opponent_highlight": "good"
    },
    {
      "name": "Trevor Mcdonald",
      "date": "2026-07-12",
      "pitcher_team": "SF",
      "opponent_team": "COL",
      "home_away": "home",
      "game_time_pt": "1:05 PM PT",
      "availability": "free_agent",
      "stats": {
        "wins": 3,
        "losses": 7,
        "era": "5.46",
        "whip": "1.38",
        "innings_pitched": "59.1",
        "strikeouts": 50,
        "highlights": {
          "era": "warn",
          "whip": null,
          "k_per_9": null
        }
      },
      "opposing_pitcher_name": "Michael Lorenzen",
      "yahoo_gamelog_url": "https://sports.yahoo.com/mlb/players/60389/gamelog/",
      "opponent_highlight": "bad"
    },
    {
      "name": "Noah Schultz",
      "date": "2026-07-12",
      "pitcher_team": "CWS",
      "opponent_team": "ATH",
      "home_away": "home",
      "game_time_pt": "11:10 AM PT",
      "availability": "waivers",
      "stats": {
        "wins": 2,
        "losses": 6,
        "era": "6.00",
        "whip": "1.42",
        "innings_pitched": "48.0",
        "strikeouts": 43,
        "highlights": {
          "era": "warn",
          "whip": null,
          "k_per_9": null
        }
      },
      "opposing_pitcher_name": "Jt Ginn",
      "yahoo_gamelog_url": "https://sports.yahoo.com/mlb/players/60156/gamelog/",
      "opponent_highlight": "warn"
    },
    {
      "name": "Kodai Senga",
      "date": "2026-07-12",
      "pitcher_team": "NYM",
      "opponent_team": "BOS",
      "home_away": "home",
      "game_time_pt": "10:40 AM PT",
      "availability": "free_agent",
      "stats": {
        "wins": 0,
        "losses": 7,
        "era": "8.69",
        "whip": "1.75",
        "innings_pitched": "39.1",
        "strikeouts": 47,
        "highlights": {
          "era": "bad",
          "whip": "bad",
          "k_per_9": "good"
        }
      },
      "opposing_pitcher_name": "Payton Tolle",
      "yahoo_gamelog_url": "https://sports.yahoo.com/mlb/players/12776/gamelog/",
      "opponent_highlight": null
    },
    {
      "name": "Cristian Javier",
      "date": "2026-07-12",
      "pitcher_team": "HOU",
      "opponent_team": "TEX",
      "home_away": "away",
      "game_time_pt": "11:35 AM PT",
      "availability": "free_agent",
      "stats": {
        "wins": 0,
        "losses": 1,
        "era": "10.22",
        "whip": "2.27",
        "innings_pitched": "12.1",
        "strikeouts": 8,
        "highlights": {
          "era": "bad",
          "whip": "bad",
          "k_per_9": null
        }
      },
      "opposing_pitcher_name": "Jacob Degrom",
      "yahoo_gamelog_url": "https://sports.yahoo.com/mlb/players/11315/gamelog/",
      "opponent_highlight": null
    }
  ],
  "warnings": [],
  "cached_at": "2026-07-11T04:41:36-07:00"
}
